toonbuilder/__init__.py
toonbuilder/json_to_toon.py
toonbuilder/toml_to_toon.py
toonbuilder/xml_to_toon.py
toonbuilder-0.1.1.dist-info/licenses/LICENSE
toonbuilder-0.1.1.dist-info/METADATA
toonbuilder-0.1.1.dist-info/WHEEL
toonbuilder-0.1.1.dist-info/top_level.txt
toonbuilder-0.1.1.dist-info/RECORD
