Metadata-Version: 2.4
Name: toonbuilder
Version: 0.1.1
Summary: Convert JSON and XML files to TOON, a schema-aware data formatting for LLM prompts.
Author: Polybit
Project-URL: Homepage, https://github.com/0xPolybit/toonbuilder
Project-URL: Bug Tracker, https://github.com/0xPolybit/toonbuilder/issues
Classifier: Programming Language :: Python :: 3
Classifier: License :: OSI Approved :: MIT License
Classifier: Operating System :: OS Independent
Requires-Python: >=3.7
License-File: LICENSE
Dynamic: license-file
